libcasm/clexulator/__init__.py
libcasm/clexulator/_clexulator.cpython-312-x86_64-linux-gnu.so
libcasm/clexulator/_functions.py
libcasm/include/casm/clexulator/BaseClexulator.hh
libcasm/include/casm/clexulator/BasicClexParamPack.hh
libcasm/include/casm/clexulator/ClexParamPack.hh
libcasm/include/casm/clexulator/Clexulator.hh
libcasm/include/casm/clexulator/ClusterExpansion.hh
libcasm/include/casm/clexulator/ConfigDoFValues.hh
libcasm/include/casm/clexulator/ConfigDoFValuesTools.hh
libcasm/include/casm/clexulator/ConfigDoFValuesTools_impl.hh
libcasm/include/casm/clexulator/Correlations.hh
libcasm/include/casm/clexulator/DiffClexParamPack.hh
libcasm/include/casm/clexulator/DoFSpace.hh
libcasm/include/casm/clexulator/DoFSpaceAxisInfo.hh
libcasm/include/casm/clexulator/ImpactTable.hh
libcasm/include/casm/clexulator/LocalClusterExpansion.hh
libcasm/include/casm/clexulator/LocalCorrelations.hh
libcasm/include/casm/clexulator/NeighborList.hh
libcasm/include/casm/clexulator/OrderParameter.hh
libcasm/include/casm/clexulator/SparseCoefficients.hh
libcasm/include/casm/clexulator/version.hh
libcasm/include/casm/clexulator/external/fadbad/badiff.h
libcasm/include/casm/clexulator/external/fadbad/fadbad.h
libcasm/include/casm/clexulator/external/fadbad/fadiff.h
libcasm/include/casm/clexulator/external/fadbad/tadiff.h
libcasm/include/casm/clexulator/io/json/Clexulator_json_io.hh
libcasm/include/casm/clexulator/io/json/ConfigDoFValues_json_io.hh
libcasm/include/casm/clexulator/io/json/DoFSpace_json_io.hh
libcasm/include/casm/clexulator/io/json/SparseCoefficients_json_io.hh
libcasm/lib/libcasm_clexulator.so
libcasm/share/CASMcode_clexulator/cmake/CASMcode_clexulatorConfig.cmake
libcasm/share/CASMcode_clexulator/cmake/CASMcode_clexulatorConfigVersion.cmake
libcasm/share/CASMcode_clexulator/cmake/CASMcode_clexulatorTargets-release.cmake
libcasm/share/CASMcode_clexulator/cmake/CASMcode_clexulatorTargets.cmake
libcasm_clexulator-2.3.0.dist-info/licenses/LICENSE
libcasm_clexulator-2.3.0.dist-info/METADATA
libcasm_clexulator-2.3.0.dist-info/WHEEL
libcasm_clexulator-2.3.0.dist-info/top_level.txt
libcasm_clexulator-2.3.0.dist-info/RECORD
